evenoddsjy/__init__.py
evenoddsjy/__main__.py
evenoddsjy/cli.py
evenoddsjy/gui.py
evenoddsjy/tests/__init__.py
evenoddsjy/tests/conftest.py
evenoddsjy/tests/test_utils.py
evenoddsjy/utils.py
evenoddsjy-0.1.dist-info/entry_points.txt
evenoddsjy-0.1.dist-info/LICENSE.md
evenoddsjy-0.1.dist-info/METADATA
evenoddsjy-0.1.dist-info/WHEEL
evenoddsjy-0.1.dist-info/RECORD
