Metadata-Version: 2.1
Name: evenoddsjy
Version: 0.1
Summary: test desc
Home-page: https://pypi.org/project/evenoddsjy
License: MIT
Author: Sanjay Soundarajan
Author-email: you@yourdomain.com
Requires-Python: >=3.10,<4.0
Classifier: Development Status :: 1 - Planning
Classifier: License :: OSI Approved :: MIT License
Classifier: Natural Language :: English
Classifier: Operating System :: OS Independent
Classifier: Programming Language :: Python
Classifier: Programming Language :: Python :: 3
Classifier: Programming Language :: Python :: 3.10
Classifier: Programming Language :: Python :: 3.11
Classifier: Programming Language :: Python :: 3
Classifier: Programming Language :: Python :: 3.11
Requires-Dist: click
Requires-Dist: minilog
Project-URL: Documentation, https://evenoddsjy.readthedocs.io
Project-URL: Repository, https://github.com/megasanjay/evenoddsjy
